{
  "target_column": "ACEDEPRS",
  "accuracy": 0.7914882226980728,
  "classification_report": {
    "1.0": {
      "precision": 0.5764192139737991,
      "recall": 0.06223479490806223,
      "f1-score": 0.1123404255319149,
      "support": 2121.0
    },
    "2.0": {
      "precision": 0.795974132434648,
      "recall": 0.989918441323063,
      "f1-score": 0.8824153077194931,
      "support": 8828.0
    },
    "7.0": {
      "precision": 0.0,
      "recall": 0.0,
      "f1-score": 0.0,
      "support": 121.0
    },
    "9.0": {
      "precision": 0.0,
      "recall": 0.0,
      "f1-score": 0.0,
      "support": 138.0
    },
    "accuracy": 0.7914882226980728,
    "macro avg": {
      "precision": 0.34309833660211175,
      "recall": 0.2630383090577813,
      "f1-score": 0.248688933312852,
      "support": 11208.0
    },
    "weighted avg": {
      "precision": 0.7360318338661225,
      "recall": 0.7914882226980728,
      "f1-score": 0.7162951801481866,
      "support": 11208.0
    }
  },
  "feature_importance": [
    {
      "feature": "_AGE80",
      "importance": 0.3472236135966485
    },
    {
      "feature": "EMPLOY1",
      "importance": 0.1108246197095075
    },
    {
      "feature": "_IMPRACE",
      "importance": 0.09143381111167455
    },
    {
      "feature": "INCOME3",
      "importance": 0.08224518721522159
    },
    {
      "feature": "MARITAL",
      "importance": 0.07820274466089928
    },
    {
      "feature": "SEXVAR",
      "importance": 0.07445741714466467
    },
    {
      "feature": "RENTHOM1",
      "importance": 0.06424771323463338
    },
    {
      "feature": "EDUCA",
      "importance": 0.05469515343030654
    },
    {
      "feature": "CHILDREN",
      "importance": 0.03786161458454915
    },
    {
      "feature": "_HISPANC",
      "importance": 0.02523820625832958
    },
    {
      "feature": "CPDEMO1C",
      "importance": 0.02132149825003358
    },
    {
      "feature": "VETERAN3",
      "importance": 0.012248420803531685
    }
  ],
  "confusion_matrix": [
    [
      132,
      1989,
      0,
      0
    ],
    [
      89,
      8739,
      0,
      0
    ],
    [
      6,
      115,
      0,
      0
    ],
    [
      2,
      136,
      0,
      0
    ]
  ],
  "class_labels": [
    "Yes",
    "No",
    "Don't know/Not Sure",
    "Refused"
  ],
  "model_parameters": {
    "n_estimators": 100,
    "max_depth": 10,
    "min_samples_split": 10,
    "min_samples_leaf": 5,
    "random_state": 42,
    "n_jobs": -1
  },
  "analysis_metadata": {
    "total_samples": 56040,
    "training_samples": 44832,
    "test_samples": 11208,
    "features_used": [
      "MARITAL",
      "EDUCA",
      "RENTHOM1",
      "CPDEMO1C",
      "VETERAN3",
      "EMPLOY1",
      "CHILDREN",
      "INCOME3",
      "SEXVAR",
      "_HISPANC",
      "_IMPRACE",
      "_AGE80"
    ],
    "features_dropped_missing": 4,
    "target_missing_dropped": 377283,
    "hyperparameter_tuning": false,
    "analysis_time_seconds": 0.3412642478942871,
    "target_distribution": {
      "1.0": 10606,
      "2.0": 44138,
      "7.0": 604,
      "9.0": 692
    }
  },
  "successful": true,
  "error_message": null
}