{
  "target_column": "ASTHMA3",
  "accuracy": 0.8475606941752054,
  "classification_report": {
    "1.0": {
      "precision": 0.75,
      "recall": 0.00023304591004427873,
      "f1-score": 0.00046594703735342084,
      "support": 12873.0
    },
    "2.0": {
      "precision": 0.847565197322871,
      "recall": 0.9999863854814774,
      "f1-score": 0.9174884923584263,
      "support": 73451.0
    },
    "7.0": {
      "precision": 0.0,
      "recall": 0.0,
      "f1-score": 0.0,
      "support": 289.0
    },
    "9.0": {
      "precision": 0.0,
      "recall": 0.0,
      "f1-score": 0.0,
      "support": 51.0
    },
    "accuracy": 0.8475606941752054,
    "macro avg": {
      "precision": 0.3993912993307177,
      "recall": 0.25005485784788045,
      "f1-score": 0.22948860984894495,
      "support": 86664.0
    },
    "weighted avg": {
      "precision": 0.8297477765688427,
      "recall": 0.8475606941752054,
      "f1-score": 0.7776752214117815,
      "support": 86664.0
    }
  },
  "feature_importance": [
    {
      "feature": "EMPLOY1",
      "importance": 0.26395839551044686
    },
    {
      "feature": "_SEX",
      "importance": 0.15467605753551197
    },
    {
      "feature": "_AGE80",
      "importance": 0.14997346729173314
    },
    {
      "feature": "INCOME3",
      "importance": 0.0793244733469147
    },
    {
      "feature": "RENTHOM1",
      "importance": 0.07112580880459271
    },
    {
      "feature": "MARITAL",
      "importance": 0.059993475127676964
    },
    {
      "feature": "EDUCA",
      "importance": 0.05479282176022996
    },
    {
      "feature": "_IMPRACE",
      "importance": 0.05228897409042665
    },
    {
      "feature": "CHILDREN",
      "importance": 0.02939450242398063
    },
    {
      "feature": "VETERAN3",
      "importance": 0.02879606185258872
    },
    {
      "feature": "CPDEMO1C",
      "importance": 0.028059456007470278
    },
    {
      "feature": "_HISPANC",
      "importance": 0.027616506248427323
    }
  ],
  "confusion_matrix": [
    [
      3,
      12870,
      0,
      0
    ],
    [
      1,
      73450,
      0,
      0
    ],
    [
      0,
      289,
      0,
      0
    ],
    [
      0,
      51,
      0,
      0
    ]
  ],
  "class_labels": [
    "Yes",
    "No -  Go to Section 07.06 CHCSCNC1",
    "Don't know/Not Sure -  Go to Section 07.06 CHCSCNC1",
    "Refused -  Go to Section 07.06 CHCSCNC1"
  ],
  "model_parameters": {
    "n_estimators": 100,
    "max_depth": 10,
    "min_samples_split": 10,
    "min_samples_leaf": 5,
    "random_state": 42,
    "n_jobs": -1
  },
  "analysis_metadata": {
    "total_samples": 433320,
    "training_samples": 346656,
    "test_samples": 86664,
    "features_used": [
      "MARITAL",
      "EDUCA",
      "RENTHOM1",
      "CPDEMO1C",
      "VETERAN3",
      "EMPLOY1",
      "CHILDREN",
      "INCOME3",
      "_HISPANC",
      "_IMPRACE",
      "_SEX",
      "_AGE80"
    ],
    "features_dropped_missing": 4,
    "target_missing_dropped": 3,
    "hyperparameter_tuning": false,
    "analysis_time_seconds": 2.5677261352539062,
    "target_distribution": {
      "1.0": 64366,
      "2.0": 367256,
      "7.0": 1444,
      "9.0": 254
    }
  },
  "successful": true,
  "error_message": null
}