{
  "target_column": "GENHLTH",
  "accuracy": 0.40088156558663346,
  "classification_report": {
    "1.0": {
      "precision": 1.0,
      "recall": 0.00015770383220312253,
      "f1-score": 0.000315357931251971,
      "support": 12682.0
    },
    "2.0": {
      "precision": 0.419851152139688,
      "recall": 0.6192520142138409,
      "f1-score": 0.5004193617172507,
      "support": 28423.0
    },
    "3.0": {
      "precision": 0.3833614821638774,
      "recall": 0.5194161292559462,
      "f1-score": 0.44113663133097764,
      "support": 28842.0
    },
    "4.0": {
      "precision": 0.3802233429394813,
      "recall": 0.17036558792672102,
      "f1-score": 0.23530067435768823,
      "support": 12391.0
    },
    "5.0": {
      "precision": 0.42727272727272725,
      "recall": 0.011533742331288344,
      "f1-score": 0.022461170848267622,
      "support": 4075.0
    },
    "7.0": {
      "precision": 0.0,
      "recall": 0.0,
      "f1-score": 0.0,
      "support": 179.0
    },
    "9.0": {
      "precision": 0.0,
      "recall": 0.0,
      "f1-score": 0.0,
      "support": 72.0
    },
    "accuracy": 0.40088156558663346,
    "macro avg": {
      "precision": 0.37295838635939627,
      "recall": 0.1886750253657142,
      "f1-score": 0.17137617088363372,
      "support": 86664.0
    },
    "weighted avg": {
      "precision": 0.48607062877130497,
      "recall": 0.40088156558663346,
      "f1-score": 0.3456778078024833,
      "support": 86664.0
    }
  },
  "feature_importance": [
    {
      "feature": "EMPLOY1",
      "importance": 0.29061877119223334
    },
    {
      "feature": "INCOME3",
      "importance": 0.22266170256462836
    },
    {
      "feature": "EDUCA",
      "importance": 0.1733735447297142
    },
    {
      "feature": "_AGE80",
      "importance": 0.10947358758648423
    },
    {
      "feature": "_IMPRACE",
      "importance": 0.05778548622955264
    },
    {
      "feature": "RENTHOM1",
      "importance": 0.036295305085126954
    },
    {
      "feature": "MARITAL",
      "importance": 0.035236673877559056
    },
    {
      "feature": "_HISPANC",
      "importance": 0.01875224203370119
    },
    {
      "feature": "CHILDREN",
      "importance": 0.016933942040706244
    },
    {
      "feature": "CPDEMO1C",
      "importance": 0.014775935052763162
    },
    {
      "feature": "SEXVAR",
      "importance": 0.013929839261307192
    },
    {
      "feature": "VETERAN3",
      "importance": 0.010162970346223514
    }
  ],
  "confusion_matrix": [
    [
      2,
      8223,
      4289,
      168,
      0,
      0,
      0
    ],
    [
      0,
      17601,
      10439,
      378,
      5,
      0,
      0
    ],
    [
      0,
      12448,
      14981,
      1394,
      19,
      0,
      0
    ],
    [
      0,
      3006,
      7236,
      2111,
      38,
      0,
      0
    ],
    [
      0,
      585,
      1972,
      1471,
      47,
      0,
      0
    ],
    [
      0,
      40,
      118,
      21,
      0,
      0,
      0
    ],
    [
      0,
      19,
      43,
      9,
      1,
      0,
      0
    ]
  ],
  "class_labels": [
    "Excellent",
    "Very good",
    "Good",
    "Fair",
    "Poor",
    "Don't know/Not Sure",
    "Refused"
  ],
  "model_parameters": {
    "n_estimators": 100,
    "max_depth": 10,
    "min_samples_split": 10,
    "min_samples_leaf": 5,
    "random_state": 42,
    "n_jobs": -1
  },
  "analysis_metadata": {
    "total_samples": 433319,
    "training_samples": 346655,
    "test_samples": 86664,
    "features_used": [
      "MARITAL",
      "EDUCA",
      "RENTHOM1",
      "CPDEMO1C",
      "VETERAN3",
      "EMPLOY1",
      "CHILDREN",
      "INCOME3",
      "SEXVAR",
      "_HISPANC",
      "_IMPRACE",
      "_AGE80"
    ],
    "features_dropped_missing": 4,
    "target_missing_dropped": 4,
    "hyperparameter_tuning": false,
    "analysis_time_seconds": 5.041607856750488,
    "target_distribution": {
      "1.0": 63410,
      "2.0": 142115,
      "3.0": 144209,
      "4.0": 61955,
      "5.0": 20372,
      "7.0": 897,
      "9.0": 361
    }
  },
  "successful": true,
  "error_message": null
}