{
  "target_column": "INSULIN1",
  "accuracy": 0.6734651833539349,
  "classification_report": {
    "1.0": {
      "precision": 0.4928571428571429,
      "recall": 0.04423076923076923,
      "f1-score": 0.0811764705882353,
      "support": 1560.0
    },
    "2.0": {
      "precision": 0.6788290199406024,
      "recall": 0.9785932721712538,
      "f1-score": 0.8016032064128257,
      "support": 3270.0
    },
    "7.0": {
      "precision": 0.0,
      "recall": 0.0,
      "f1-score": 0.0,
      "support": 20.0
    },
    "9.0": {
      "precision": 0.0,
      "recall": 0.0,
      "f1-score": 0.0,
      "support": 4.0
    },
    "accuracy": 0.6734651833539349,
    "macro avg": {
      "precision": 0.2929215406994363,
      "recall": 0.2557060103505058,
      "f1-score": 0.22069491925026524,
      "support": 4854.0
    },
    "weighted avg": {
      "precision": 0.6157041693578311,
      "recall": 0.6734651833539349,
      "f1-score": 0.5661058465363796,
      "support": 4854.0
    }
  },
  "feature_importance": [
    {
      "feature": "_AGE80",
      "importance": 0.22245218268203604
    },
    {
      "feature": "EMPLOY1",
      "importance": 0.17963342409976465
    },
    {
      "feature": "INCOME3",
      "importance": 0.1451090729683244
    },
    {
      "feature": "EDUCA",
      "importance": 0.08372626670887004
    },
    {
      "feature": "MARITAL",
      "importance": 0.07737703571317653
    },
    {
      "feature": "_IMPRACE",
      "importance": 0.06736330644240919
    },
    {
      "feature": "RENTHOM1",
      "importance": 0.053767331825043764
    },
    {
      "feature": "CHILDREN",
      "importance": 0.046461649483905264
    },
    {
      "feature": "CPDEMO1C",
      "importance": 0.045374378317755704
    },
    {
      "feature": "_SEX",
      "importance": 0.03595425463600584
    },
    {
      "feature": "_HISPANC",
      "importance": 0.025287798240421492
    },
    {
      "feature": "VETERAN3",
      "importance": 0.01749329888228705
    }
  ],
  "confusion_matrix": [
    [
      69,
      1491,
      0,
      0
    ],
    [
      70,
      3200,
      0,
      0
    ],
    [
      1,
      19,
      0,
      0
    ],
    [
      0,
      4,
      0,
      0
    ]
  ],
  "class_labels": [
    "Yes",
    "No",
    "Don't know/Not Sure",
    "Refused"
  ],
  "model_parameters": {
    "n_estimators": 100,
    "max_depth": 10,
    "min_samples_split": 10,
    "min_samples_leaf": 5,
    "random_state": 42,
    "n_jobs": -1
  },
  "analysis_metadata": {
    "total_samples": 24268,
    "training_samples": 19414,
    "test_samples": 4854,
    "features_used": [
      "MARITAL",
      "EDUCA",
      "RENTHOM1",
      "CPDEMO1C",
      "VETERAN3",
      "EMPLOY1",
      "CHILDREN",
      "INCOME3",
      "_HISPANC",
      "_IMPRACE",
      "_SEX",
      "_AGE80"
    ],
    "features_dropped_missing": 4,
    "target_missing_dropped": 409055,
    "hyperparameter_tuning": false,
    "analysis_time_seconds": 0.22061419486999512,
    "target_distribution": {
      "1.0": 7802,
      "2.0": 16347,
      "7.0": 101,
      "9.0": 18
    }
  },
  "successful": true,
  "error_message": null
}